metamenth/__init__.py
metamenth/controls/__init__.py
metamenth/controls/abstract_control.py
metamenth/controls/binary_controls/__init__.py
metamenth/controls/binary_controls/abstract_binary_control.py
metamenth/controls/pid_controls/__init__.py
metamenth/controls/pid_controls/abstract_pid_controls.py
metamenth/datatypes/__init__.py
metamenth/datatypes/address.py
metamenth/datatypes/binary_measure.py
metamenth/datatypes/continuous_measure.py
metamenth/datatypes/exponential_measure.py
metamenth/datatypes/linear_measure.py
metamenth/datatypes/measure.py
metamenth/datatypes/observable_message.py
metamenth/datatypes/operational_schedule.py
metamenth/datatypes/point.py
metamenth/datatypes/rated_device_measure.py
metamenth/datatypes/schedulable_entity.py
metamenth/datatypes/interfaces/__init__.py
metamenth/datatypes/interfaces/abstract_dynamic_entity.py
metamenth/datatypes/interfaces/abstract_measure.py
metamenth/datatypes/interfaces/abstract_range_measure.py
metamenth/datatypes/relationships/__init__.py
metamenth/datatypes/relationships/one_to_many.py
metamenth/datatypes/relationships/interfaces/__init__.py
metamenth/datatypes/relationships/interfaces/abstract_relationship.py
metamenth/energysystem/__init__.py
metamenth/energysystem/engine.py
metamenth/energysystem/non_renewable_energy_system.py
metamenth/energysystem/renewable_energy_system.py
metamenth/energysystem/solar_pv.py
metamenth/energysystem/wind_mill.py
metamenth/energysystem/electricals/__init__.py
metamenth/energysystem/electricals/alternator.py
metamenth/energysystem/electricals/automatic_transfer_switch.py
metamenth/energysystem/electricals/uninterruptible_power_supply.py
metamenth/energysystem/interfaces/__init__.py
metamenth/energysystem/interfaces/abstract_common_energy_system.py
metamenth/energysystem/interfaces/abstract_electrical.py
metamenth/energysystem/interfaces/abstract_energy_system.py
metamenth/energysystem/storage_system/__init__.py
metamenth/energysystem/storage_system/battery.py
metamenth-1.0.8.dist-info/LICENSE
metamenth-1.0.8.dist-info/METADATA
metamenth-1.0.8.dist-info/WHEEL
metamenth-1.0.8.dist-info/top_level.txt
metamenth-1.0.8.dist-info/RECORD
