Metadata-Version: 2.1
Name: metamenth
Version: 1.0.8
Summary: Metamodel for Energy Things (MetamEnTh) is an object-oriented metamodel designed to model the operational aspects of buildings. It focuses on the relationships and interactions between mechanical, electrical, and plumbing (MEP) entities and their connections to sensors and spatial entities such as rooms and open spaces within buildings.
Home-page: https://github.com/ptidejteam/metamenth
Author: Peter Yefi
Author-email: peteryefi@gmail.com
License: Apache License 2.0
Classifier: Programming Language :: Python :: 3
Classifier: License :: OSI Approved :: Apache Software License
Classifier: Operating System :: OS Independent
Requires-Python: >=3.6
License-File: LICENSE
Requires-Dist: coverage==7.4.1
Requires-Dist: fuzzywuzzy==0.18.0
Requires-Dist: Levenshtein==0.25.0
Requires-Dist: python-Levenshtein==0.25.0
Requires-Dist: rapidfuzz==3.6.1
